
{
  "projects": {
    "contentflow": {
      "url": "/contentflow.jpg",
      "hint": "social media dashboard"
    },
    "rag": {
      "url": "/rag.jpg",
      "hint": "artificial intelligence"
    },
    "hotel": {
      "url": "/hotel.jpg",
      "hint": "luxury hotel"
    },
    "youth": {
      "url": "/youth.jpg",
      "hint": "community group"
    },
    "cars": {
      "url": "/cars.jpg",
      "hint": "luxury cars"
    },
    "timber": {
      "url": "/timber.jpg",
      "hint": "timber furniture"
    }
  }
}
